{
  "type": "File",
  "start": 0,
  "end": 251,
  "loc": {
    "start": {
      "line": 1,
      "column": 0
    },
    "end": {
      "line": 14,
      "column": 0
    }
  },
  "program": {
    "type": "Program",
    "start": 0,
    "end": 251,
    "loc": {
      "start": {
        "line": 1,
        "column": 0
      },
      "end": {
        "line": 14,
        "column": 0
      }
    },
    "sourceType": "module",
    "body": [
      {
        "type": "ImportDeclaration",
        "start": 0,
        "end": 40,
        "loc": {
          "start": {
            "line": 1,
            "column": 0
          },
          "end": {
            "line": 1,
            "column": 40
          }
        },
        "specifiers": [
          {
            "type": "ImportDefaultSpecifier",
            "start": 7,
            "end": 22,
            "loc": {
              "start": {
                "line": 1,
                "column": 7
              },
              "end": {
                "line": 1,
                "column": 22
              }
            },
            "local": {
              "type": "Identifier",
              "start": 7,
              "end": 22,
              "loc": {
                "start": {
                  "line": 1,
                  "column": 7
                },
                "end": {
                  "line": 1,
                  "column": 22
                },
                "identifierName": "ExtendableError"
              },
              "name": "ExtendableError"
            }
          }
        ],
        "source": {
          "type": "StringLiteral",
          "start": 28,
          "end": 39,
          "loc": {
            "start": {
              "line": 1,
              "column": 28
            },
            "end": {
              "line": 1,
              "column": 39
            }
          },
          "extra": {
            "rawValue": "es6-error",
            "raw": "'es6-error'"
          },
          "value": "es6-error"
        }
      },
      {
        "type": "Identifier",
        "start": 42,
        "end": 217,
        "loc": {
          "start": {
            "line": 3,
            "column": 0
          },
          "end": {
            "line": 11,
            "column": 1
          }
        },
        "id": {
          "type": "Identifier",
          "start": 48,
          "end": 63,
          "loc": {
            "start": {
              "line": 3,
              "column": 6
            },
            "end": {
              "line": 3,
              "column": 21
            },
            "identifierName": "ValidationError"
          },
          "name": "ValidationError"
        },
        "superClass": {
          "type": "Identifier",
          "start": 72,
          "end": 87,
          "loc": {
            "start": {
              "line": 3,
              "column": 30
            },
            "end": {
              "line": 3,
              "column": 45
            },
            "identifierName": "ExtendableError"
          },
          "name": "ExtendableError"
        },
        "body": {
          "type": "ClassBody",
          "start": 88,
          "end": 217,
          "loc": {
            "start": {
              "line": 3,
              "column": 46
            },
            "end": {
              "line": 11,
              "column": 1
            }
          },
          "body": [
            {
              "type": "ClassMethod",
              "start": 92,
              "end": 215,
              "loc": {
                "start": {
                  "line": 4,
                  "column": 2
                },
                "end": {
                  "line": 10,
                  "column": 3
                }
              },
              "static": false,
              "computed": false,
              "key": {
                "type": "Identifier",
                "start": 92,
                "end": 103,
                "loc": {
                  "start": {
                    "line": 4,
                    "column": 2
                  },
                  "end": {
                    "line": 4,
                    "column": 13
                  },
                  "identifierName": "constructor"
                },
                "name": "constructor"
              },
              "kind": "constructor",
              "id": null,
              "generator": false,
              "expression": false,
              "async": false,
              "params": [
                {
                  "type": "Identifier",
                  "start": 104,
                  "end": 111,
                  "loc": {
                    "start": {
                      "line": 4,
                      "column": 14
                    },
                    "end": {
                      "line": 4,
                      "column": 21
                    },
                    "identifierName": "message"
                  },
                  "name": "message"
                }
              ],
              "body": {
                "type": "BlockStatement",
                "start": 113,
                "end": 215,
                "loc": {
                  "start": {
                    "line": 4,
                    "column": 23
                  },
                  "end": {
                    "line": 10,
                    "column": 3
                  }
                },
                "body": [
                  {
                    "type": "ExpressionStatement",
                    "start": 119,
                    "end": 134,
                    "loc": {
                      "start": {
                        "line": 5,
                        "column": 4
                      },
                      "end": {
                        "line": 5,
                        "column": 19
                      }
                    },
                    "expression": {
                      "type": "CallExpression",
                      "start": 119,
                      "end": 133,
                      "loc": {
                        "start": {
                          "line": 5,
                          "column": 4
                        },
                        "end": {
                          "line": 5,
                          "column": 18
                        }
                      },
                      "callee": {
                        "type": "Super",
                        "start": 119,
                        "end": 124,
                        "loc": {
                          "start": {
                            "line": 5,
                            "column": 4
                          },
                          "end": {
                            "line": 5,
                            "column": 9
                          }
                        }
                      },
                      "arguments": [
                        {
                          "type": "Identifier",
                          "start": 125,
                          "end": 132,
                          "loc": {
                            "start": {
                              "line": 5,
                              "column": 10
                            },
                            "end": {
                              "line": 5,
                              "column": 17
                            },
                            "identifierName": "message"
                          },
                          "name": "message"
                        }
                      ]
                    }
                  },
                  {
                    "type": "ExpressionStatement",
                    "start": 140,
                    "end": 211,
                    "loc": {
                      "start": {
                        "line": 7,
                        "column": 4
                      },
                      "end": {
                        "line": 9,
                        "column": 7
                      }
                    },
                    "expression": {
                      "type": "CallExpression",
                      "start": 140,
                      "end": 210,
                      "loc": {
                        "start": {
                          "line": 7,
                          "column": 4
                        },
                        "end": {
                          "line": 9,
                          "column": 6
                        }
                      },
                      "callee": {
                        "type": "MemberExpression",
                        "start": 140,
                        "end": 161,
                        "loc": {
                          "start": {
                            "line": 7,
                            "column": 4
                          },
                          "end": {
                            "line": 7,
                            "column": 25
                          }
                        },
                        "object": {
                          "type": "Identifier",
                          "start": 140,
                          "end": 146,
                          "loc": {
                            "start": {
                              "line": 7,
                              "column": 4
                            },
                            "end": {
                              "line": 7,
                              "column": 10
                            },
                            "identifierName": "Object"
                          },
                          "name": "Object"
                        },
                        "property": {
                          "type": "Identifier",
                          "start": 147,
                          "end": 161,
                          "loc": {
                            "start": {
                              "line": 7,
                              "column": 11
                            },
                            "end": {
                              "line": 7,
                              "column": 25
                            },
                            "identifierName": "defineProperty"
                          },
                          "name": "defineProperty"
                        },
                        "computed": false
                      },
                      "arguments": [
                        {
                          "type": "ThisExpression",
                          "start": 162,
                          "end": 166,
                          "loc": {
                            "start": {
                              "line": 7,
                              "column": 26
                            },
                            "end": {
                              "line": 7,
                              "column": 30
                            }
                          }
                        },
                        {
                          "type": "StringLiteral",
                          "start": 168,
                          "end": 177,
                          "loc": {
                            "start": {
                              "line": 7,
                              "column": 32
                            },
                            "end": {
                              "line": 7,
                              "column": 41
                            }
                          },
                          "extra": {
                            "rawValue": "message",
                            "raw": "'message'"
                          },
                          "value": "message"
                        },
                        {
                          "type": "ObjectExpression",
                          "start": 179,
                          "end": 209,
                          "loc": {
                            "start": {
                              "line": 7,
                              "column": 43
                            },
                            "end": {
                              "line": 9,
                              "column": 5
                            }
                          },
                          "properties": [
                            {
                              "type": "ObjectProperty",
                              "start": 187,
                              "end": 203,
                              "loc": {
                                "start": {
                                  "line": 8,
                                  "column": 6
                                },
                                "end": {
                                  "line": 8,
                                  "column": 22
                                }
                              },
                              "method": false,
                              "shorthand": false,
                              "computed": false,
                              "key": {
                                "type": "Identifier",
                                "start": 187,
                                "end": 197,
                                "loc": {
                                  "start": {
                                    "line": 8,
                                    "column": 6
                                  },
                                  "end": {
                                    "line": 8,
                                    "column": 16
                                  },
                                  "identifierName": "enumerable"
                                },
                                "name": "enumerable"
                              },
                              "value": {
                                "type": "BooleanLiteral",
                                "start": 199,
                                "end": 203,
                                "loc": {
                                  "start": {
                                    "line": 8,
                                    "column": 18
                                  },
                                  "end": {
                                    "line": 8,
                                    "column": 22
                                  }
                                },
                                "value": true
                              }
                            }
                          ]
                        }
                      ]
                    }
                  }
                ],
                "directives": []
              }
            }
          ]
        },
        "name": "_",
        "leadingComments": [],
        "trailingComments": []
      },
      {
        "type": "Identifier",
        "start": 219,
        "end": 250,
        "loc": {
          "start": {
            "line": 13,
            "column": 0
          },
          "end": {
            "line": 13,
            "column": 31
          }
        },
        "declaration": {
          "type": "Identifier",
          "start": 234,
          "end": 249,
          "loc": {
            "start": {
              "line": 13,
              "column": 15
            },
            "end": {
              "line": 13,
              "column": 30
            },
            "identifierName": "ValidationError"
          },
          "name": "ValidationError"
        },
        "name": "_",
        "leadingComments": [],
        "trailingComments": []
      },
      {
        "type": "ExportDefaultDeclaration",
        "start": 219,
        "end": 250,
        "loc": {
          "start": {
            "line": 13,
            "column": 0
          },
          "end": {
            "line": 13,
            "column": 31
          }
        },
        "declaration": {
          "type": "ClassDeclaration",
          "start": 42,
          "end": 217,
          "loc": {
            "start": {
              "line": 3,
              "column": 0
            },
            "end": {
              "line": 11,
              "column": 1
            }
          },
          "id": {
            "type": "Identifier",
            "start": 48,
            "end": 63,
            "loc": {
              "start": {
                "line": 3,
                "column": 6
              },
              "end": {
                "line": 3,
                "column": 21
              },
              "identifierName": "ValidationError"
            },
            "name": "ValidationError"
          },
          "superClass": {
            "type": "Identifier",
            "start": 72,
            "end": 87,
            "loc": {
              "start": {
                "line": 3,
                "column": 30
              },
              "end": {
                "line": 3,
                "column": 45
              },
              "identifierName": "ExtendableError"
            },
            "name": "ExtendableError"
          },
          "body": {
            "type": "ClassBody",
            "start": 88,
            "end": 217,
            "loc": {
              "start": {
                "line": 3,
                "column": 46
              },
              "end": {
                "line": 11,
                "column": 1
              }
            },
            "body": [
              {
                "type": "ClassMethod",
                "start": 92,
                "end": 215,
                "loc": {
                  "start": {
                    "line": 4,
                    "column": 2
                  },
                  "end": {
                    "line": 10,
                    "column": 3
                  }
                },
                "static": false,
                "computed": false,
                "key": {
                  "type": "Identifier",
                  "start": 92,
                  "end": 103,
                  "loc": {
                    "start": {
                      "line": 4,
                      "column": 2
                    },
                    "end": {
                      "line": 4,
                      "column": 13
                    },
                    "identifierName": "constructor"
                  },
                  "name": "constructor"
                },
                "kind": "constructor",
                "id": null,
                "generator": false,
                "expression": false,
                "async": false,
                "params": [
                  {
                    "type": "Identifier",
                    "start": 104,
                    "end": 111,
                    "loc": {
                      "start": {
                        "line": 4,
                        "column": 14
                      },
                      "end": {
                        "line": 4,
                        "column": 21
                      },
                      "identifierName": "message"
                    },
                    "name": "message"
                  }
                ],
                "body": {
                  "type": "BlockStatement",
                  "start": 113,
                  "end": 215,
                  "loc": {
                    "start": {
                      "line": 4,
                      "column": 23
                    },
                    "end": {
                      "line": 10,
                      "column": 3
                    }
                  },
                  "body": [
                    {
                      "type": "ExpressionStatement",
                      "start": 119,
                      "end": 134,
                      "loc": {
                        "start": {
                          "line": 5,
                          "column": 4
                        },
                        "end": {
                          "line": 5,
                          "column": 19
                        }
                      },
                      "expression": {
                        "type": "CallExpression",
                        "start": 119,
                        "end": 133,
                        "loc": {
                          "start": {
                            "line": 5,
                            "column": 4
                          },
                          "end": {
                            "line": 5,
                            "column": 18
                          }
                        },
                        "callee": {
                          "type": "Super",
                          "start": 119,
                          "end": 124,
                          "loc": {
                            "start": {
                              "line": 5,
                              "column": 4
                            },
                            "end": {
                              "line": 5,
                              "column": 9
                            }
                          }
                        },
                        "arguments": [
                          {
                            "type": "Identifier",
                            "start": 125,
                            "end": 132,
                            "loc": {
                              "start": {
                                "line": 5,
                                "column": 10
                              },
                              "end": {
                                "line": 5,
                                "column": 17
                              },
                              "identifierName": "message"
                            },
                            "name": "message"
                          }
                        ]
                      }
                    },
                    {
                      "type": "ExpressionStatement",
                      "start": 140,
                      "end": 211,
                      "loc": {
                        "start": {
                          "line": 7,
                          "column": 4
                        },
                        "end": {
                          "line": 9,
                          "column": 7
                        }
                      },
                      "expression": {
                        "type": "CallExpression",
                        "start": 140,
                        "end": 210,
                        "loc": {
                          "start": {
                            "line": 7,
                            "column": 4
                          },
                          "end": {
                            "line": 9,
                            "column": 6
                          }
                        },
                        "callee": {
                          "type": "MemberExpression",
                          "start": 140,
                          "end": 161,
                          "loc": {
                            "start": {
                              "line": 7,
                              "column": 4
                            },
                            "end": {
                              "line": 7,
                              "column": 25
                            }
                          },
                          "object": {
                            "type": "Identifier",
                            "start": 140,
                            "end": 146,
                            "loc": {
                              "start": {
                                "line": 7,
                                "column": 4
                              },
                              "end": {
                                "line": 7,
                                "column": 10
                              },
                              "identifierName": "Object"
                            },
                            "name": "Object"
                          },
                          "property": {
                            "type": "Identifier",
                            "start": 147,
                            "end": 161,
                            "loc": {
                              "start": {
                                "line": 7,
                                "column": 11
                              },
                              "end": {
                                "line": 7,
                                "column": 25
                              },
                              "identifierName": "defineProperty"
                            },
                            "name": "defineProperty"
                          },
                          "computed": false
                        },
                        "arguments": [
                          {
                            "type": "ThisExpression",
                            "start": 162,
                            "end": 166,
                            "loc": {
                              "start": {
                                "line": 7,
                                "column": 26
                              },
                              "end": {
                                "line": 7,
                                "column": 30
                              }
                            }
                          },
                          {
                            "type": "StringLiteral",
                            "start": 168,
                            "end": 177,
                            "loc": {
                              "start": {
                                "line": 7,
                                "column": 32
                              },
                              "end": {
                                "line": 7,
                                "column": 41
                              }
                            },
                            "extra": {
                              "rawValue": "message",
                              "raw": "'message'"
                            },
                            "value": "message"
                          },
                          {
                            "type": "ObjectExpression",
                            "start": 179,
                            "end": 209,
                            "loc": {
                              "start": {
                                "line": 7,
                                "column": 43
                              },
                              "end": {
                                "line": 9,
                                "column": 5
                              }
                            },
                            "properties": [
                              {
                                "type": "ObjectProperty",
                                "start": 187,
                                "end": 203,
                                "loc": {
                                  "start": {
                                    "line": 8,
                                    "column": 6
                                  },
                                  "end": {
                                    "line": 8,
                                    "column": 22
                                  }
                                },
                                "method": false,
                                "shorthand": false,
                                "computed": false,
                                "key": {
                                  "type": "Identifier",
                                  "start": 187,
                                  "end": 197,
                                  "loc": {
                                    "start": {
                                      "line": 8,
                                      "column": 6
                                    },
                                    "end": {
                                      "line": 8,
                                      "column": 16
                                    },
                                    "identifierName": "enumerable"
                                  },
                                  "name": "enumerable"
                                },
                                "value": {
                                  "type": "BooleanLiteral",
                                  "start": 199,
                                  "end": 203,
                                  "loc": {
                                    "start": {
                                      "line": 8,
                                      "column": 18
                                    },
                                    "end": {
                                      "line": 8,
                                      "column": 22
                                    }
                                  },
                                  "value": true
                                }
                              }
                            ]
                          }
                        ]
                      }
                    }
                  ],
                  "directives": []
                }
              }
            ]
          },
          "__PseudoExport__": false,
          "leadingComments": [],
          "trailingComments": []
        },
        "leadingComments": null
      }
    ],
    "directives": []
  },
  "comments": [],
  "tokens": [
    {
      "type": {
        "label": "import",
        "keyword": "import",
        "beforeExpr": false,
        "startsExpr": true,
        "rightAssociative": false,
        "isLoop": false,
        "isAssign": false,
        "prefix": false,
        "postfix": false,
        "binop": null,
        "updateContext": null
      },
      "value": "import",
      "start": 0,
      "end": 6,
      "loc": {
        "start": {
          "line": 1,
          "column": 0
        },
        "end": {
          "line": 1,
          "column": 6
        }
      }
    },
    {
      "type": {
        "label": "name",
        "beforeExpr": false,
        "startsExpr": true,
        "rightAssociative": false,
        "isLoop": false,
        "isAssign": false,
        "prefix": false,
        "postfix": false,
        "binop": null
      },
      "value": "ExtendableError",
      "start": 7,
      "end": 22,
      "loc": {
        "start": {
          "line": 1,
          "column": 7
        },
        "end": {
          "line": 1,
          "column": 22
        }
      }
    },
    {
      "type": {
        "label": "name",
        "beforeExpr": false,
        "startsExpr": true,
        "rightAssociative": false,
        "isLoop": false,
        "isAssign": false,
        "prefix": false,
        "postfix": false,
        "binop": null
      },
      "value": "from",
      "start": 23,
      "end": 27,
      "loc": {
        "start": {
          "line": 1,
          "column": 23
        },
        "end": {
          "line": 1,
          "column": 27
        }
      }
    },
    {
      "type": {
        "label": "string",
        "beforeExpr": false,
        "startsExpr": true,
        "rightAssociative": false,
        "isLoop": false,
        "isAssign": false,
        "prefix": false,
        "postfix": false,
        "binop": null,
        "updateContext": null
      },
      "value": "es6-error",
      "start": 28,
      "end": 39,
      "loc": {
        "start": {
          "line": 1,
          "column": 28
        },
        "end": {
          "line": 1,
          "column": 39
        }
      }
    },
    {
      "type": {
        "label": ";",
        "beforeExpr": true,
        "startsExpr": false,
        "rightAssociative": false,
        "isLoop": false,
        "isAssign": false,
        "prefix": false,
        "postfix": false,
        "binop": null,
        "updateContext": null
      },
      "start": 39,
      "end": 40,
      "loc": {
        "start": {
          "line": 1,
          "column": 39
        },
        "end": {
          "line": 1,
          "column": 40
        }
      }
    },
    {
      "type": {
        "label": "class",
        "keyword": "class",
        "beforeExpr": false,
        "startsExpr": false,
        "rightAssociative": false,
        "isLoop": false,
        "isAssign": false,
        "prefix": false,
        "postfix": false,
        "binop": null,
        "updateContext": null
      },
      "value": "class",
      "start": 42,
      "end": 47,
      "loc": {
        "start": {
          "line": 3,
          "column": 0
        },
        "end": {
          "line": 3,
          "column": 5
        }
      }
    },
    {
      "type": {
        "label": "name",
        "beforeExpr": false,
        "startsExpr": true,
        "rightAssociative": false,
        "isLoop": false,
        "isAssign": false,
        "prefix": false,
        "postfix": false,
        "binop": null
      },
      "value": "ValidationError",
      "start": 48,
      "end": 63,
      "loc": {
        "start": {
          "line": 3,
          "column": 6
        },
        "end": {
          "line": 3,
          "column": 21
        }
      }
    },
    {
      "type": {
        "label": "extends",
        "keyword": "extends",
        "beforeExpr": true,
        "startsExpr": false,
        "rightAssociative": false,
        "isLoop": false,
        "isAssign": false,
        "prefix": false,
        "postfix": false,
        "binop": null,
        "updateContext": null
      },
      "value": "extends",
      "start": 64,
      "end": 71,
      "loc": {
        "start": {
          "line": 3,
          "column": 22
        },
        "end": {
          "line": 3,
          "column": 29
        }
      }
    },
    {
      "type": {
        "label": "name",
        "beforeExpr": false,
        "startsExpr": true,
        "rightAssociative": false,
        "isLoop": false,
        "isAssign": false,
        "prefix": false,
        "postfix": false,
        "binop": null
      },
      "value": "ExtendableError",
      "start": 72,
      "end": 87,
      "loc": {
        "start": {
          "line": 3,
          "column": 30
        },
        "end": {
          "line": 3,
          "column": 45
        }
      }
    },
    {
      "type": {
        "label": "{",
        "beforeExpr": true,
        "startsExpr": true,
        "rightAssociative": false,
        "isLoop": false,
        "isAssign": false,
        "prefix": false,
        "postfix": false,
        "binop": null
      },
      "start": 88,
      "end": 89,
      "loc": {
        "start": {
          "line": 3,
          "column": 46
        },
        "end": {
          "line": 3,
          "column": 47
        }
      }
    },
    {
      "type": {
        "label": "name",
        "beforeExpr": false,
        "startsExpr": true,
        "rightAssociative": false,
        "isLoop": false,
        "isAssign": false,
        "prefix": false,
        "postfix": false,
        "binop": null
      },
      "value": "constructor",
      "start": 92,
      "end": 103,
      "loc": {
        "start": {
          "line": 4,
          "column": 2
        },
        "end": {
          "line": 4,
          "column": 13
        }
      }
    },
    {
      "type": {
        "label": "(",
        "beforeExpr": true,
        "startsExpr": true,
        "rightAssociative": false,
        "isLoop": false,
        "isAssign": false,
        "prefix": false,
        "postfix": false,
        "binop": null
      },
      "start": 103,
      "end": 104,
      "loc": {
        "start": {
          "line": 4,
          "column": 13
        },
        "end": {
          "line": 4,
          "column": 14
        }
      }
    },
    {
      "type": {
        "label": "name",
        "beforeExpr": false,
        "startsExpr": true,
        "rightAssociative": false,
        "isLoop": false,
        "isAssign": false,
        "prefix": false,
        "postfix": false,
        "binop": null
      },
      "value": "message",
      "start": 104,
      "end": 111,
      "loc": {
        "start": {
          "line": 4,
          "column": 14
        },
        "end": {
          "line": 4,
          "column": 21
        }
      }
    },
    {
      "type": {
        "label": ")",
        "beforeExpr": false,
        "startsExpr": false,
        "rightAssociative": false,
        "isLoop": false,
        "isAssign": false,
        "prefix": false,
        "postfix": false,
        "binop": null
      },
      "start": 111,
      "end": 112,
      "loc": {
        "start": {
          "line": 4,
          "column": 21
        },
        "end": {
          "line": 4,
          "column": 22
        }
      }
    },
    {
      "type": {
        "label": "{",
        "beforeExpr": true,
        "startsExpr": true,
        "rightAssociative": false,
        "isLoop": false,
        "isAssign": false,
        "prefix": false,
        "postfix": false,
        "binop": null
      },
      "start": 113,
      "end": 114,
      "loc": {
        "start": {
          "line": 4,
          "column": 23
        },
        "end": {
          "line": 4,
          "column": 24
        }
      }
    },
    {
      "type": {
        "label": "super",
        "keyword": "super",
        "beforeExpr": false,
        "startsExpr": true,
        "rightAssociative": false,
        "isLoop": false,
        "isAssign": false,
        "prefix": false,
        "postfix": false,
        "binop": null,
        "updateContext": null
      },
      "value": "super",
      "start": 119,
      "end": 124,
      "loc": {
        "start": {
          "line": 5,
          "column": 4
        },
        "end": {
          "line": 5,
          "column": 9
        }
      }
    },
    {
      "type": {
        "label": "(",
        "beforeExpr": true,
        "startsExpr": true,
        "rightAssociative": false,
        "isLoop": false,
        "isAssign": false,
        "prefix": false,
        "postfix": false,
        "binop": null
      },
      "start": 124,
      "end": 125,
      "loc": {
        "start": {
          "line": 5,
          "column": 9
        },
        "end": {
          "line": 5,
          "column": 10
        }
      }
    },
    {
      "type": {
        "label": "name",
        "beforeExpr": false,
        "startsExpr": true,
        "rightAssociative": false,
        "isLoop": false,
        "isAssign": false,
        "prefix": false,
        "postfix": false,
        "binop": null
      },
      "value": "message",
      "start": 125,
      "end": 132,
      "loc": {
        "start": {
          "line": 5,
          "column": 10
        },
        "end": {
          "line": 5,
          "column": 17
        }
      }
    },
    {
      "type": {
        "label": ")",
        "beforeExpr": false,
        "startsExpr": false,
        "rightAssociative": false,
        "isLoop": false,
        "isAssign": false,
        "prefix": false,
        "postfix": false,
        "binop": null
      },
      "start": 132,
      "end": 133,
      "loc": {
        "start": {
          "line": 5,
          "column": 17
        },
        "end": {
          "line": 5,
          "column": 18
        }
      }
    },
    {
      "type": {
        "label": ";",
        "beforeExpr": true,
        "startsExpr": false,
        "rightAssociative": false,
        "isLoop": false,
        "isAssign": false,
        "prefix": false,
        "postfix": false,
        "binop": null,
        "updateContext": null
      },
      "start": 133,
      "end": 134,
      "loc": {
        "start": {
          "line": 5,
          "column": 18
        },
        "end": {
          "line": 5,
          "column": 19
        }
      }
    },
    {
      "type": {
        "label": "name",
        "beforeExpr": false,
        "startsExpr": true,
        "rightAssociative": false,
        "isLoop": false,
        "isAssign": false,
        "prefix": false,
        "postfix": false,
        "binop": null
      },
      "value": "Object",
      "start": 140,
      "end": 146,
      "loc": {
        "start": {
          "line": 7,
          "column": 4
        },
        "end": {
          "line": 7,
          "column": 10
        }
      }
    },
    {
      "type": {
        "label": ".",
        "beforeExpr": false,
        "startsExpr": false,
        "rightAssociative": false,
        "isLoop": false,
        "isAssign": false,
        "prefix": false,
        "postfix": false,
        "binop": null,
        "updateContext": null
      },
      "start": 146,
      "end": 147,
      "loc": {
        "start": {
          "line": 7,
          "column": 10
        },
        "end": {
          "line": 7,
          "column": 11
        }
      }
    },
    {
      "type": {
        "label": "name",
        "beforeExpr": false,
        "startsExpr": true,
        "rightAssociative": false,
        "isLoop": false,
        "isAssign": false,
        "prefix": false,
        "postfix": false,
        "binop": null
      },
      "value": "defineProperty",
      "start": 147,
      "end": 161,
      "loc": {
        "start": {
          "line": 7,
          "column": 11
        },
        "end": {
          "line": 7,
          "column": 25
        }
      }
    },
    {
      "type": {
        "label": "(",
        "beforeExpr": true,
        "startsExpr": true,
        "rightAssociative": false,
        "isLoop": false,
        "isAssign": false,
        "prefix": false,
        "postfix": false,
        "binop": null
      },
      "start": 161,
      "end": 162,
      "loc": {
        "start": {
          "line": 7,
          "column": 25
        },
        "end": {
          "line": 7,
          "column": 26
        }
      }
    },
    {
      "type": {
        "label": "this",
        "keyword": "this",
        "beforeExpr": false,
        "startsExpr": true,
        "rightAssociative": false,
        "isLoop": false,
        "isAssign": false,
        "prefix": false,
        "postfix": false,
        "binop": null,
        "updateContext": null
      },
      "value": "this",
      "start": 162,
      "end": 166,
      "loc": {
        "start": {
          "line": 7,
          "column": 26
        },
        "end": {
          "line": 7,
          "column": 30
        }
      }
    },
    {
      "type": {
        "label": ",",
        "beforeExpr": true,
        "startsExpr": false,
        "rightAssociative": false,
        "isLoop": false,
        "isAssign": false,
        "prefix": false,
        "postfix": false,
        "binop": null,
        "updateContext": null
      },
      "start": 166,
      "end": 167,
      "loc": {
        "start": {
          "line": 7,
          "column": 30
        },
        "end": {
          "line": 7,
          "column": 31
        }
      }
    },
    {
      "type": {
        "label": "string",
        "beforeExpr": false,
        "startsExpr": true,
        "rightAssociative": false,
        "isLoop": false,
        "isAssign": false,
        "prefix": false,
        "postfix": false,
        "binop": null,
        "updateContext": null
      },
      "value": "message",
      "start": 168,
      "end": 177,
      "loc": {
        "start": {
          "line": 7,
          "column": 32
        },
        "end": {
          "line": 7,
          "column": 41
        }
      }
    },
    {
      "type": {
        "label": ",",
        "beforeExpr": true,
        "startsExpr": false,
        "rightAssociative": false,
        "isLoop": false,
        "isAssign": false,
        "prefix": false,
        "postfix": false,
        "binop": null,
        "updateContext": null
      },
      "start": 177,
      "end": 178,
      "loc": {
        "start": {
          "line": 7,
          "column": 41
        },
        "end": {
          "line": 7,
          "column": 42
        }
      }
    },
    {
      "type": {
        "label": "{",
        "beforeExpr": true,
        "startsExpr": true,
        "rightAssociative": false,
        "isLoop": false,
        "isAssign": false,
        "prefix": false,
        "postfix": false,
        "binop": null
      },
      "start": 179,
      "end": 180,
      "loc": {
        "start": {
          "line": 7,
          "column": 43
        },
        "end": {
          "line": 7,
          "column": 44
        }
      }
    },
    {
      "type": {
        "label": "name",
        "beforeExpr": false,
        "startsExpr": true,
        "rightAssociative": false,
        "isLoop": false,
        "isAssign": false,
        "prefix": false,
        "postfix": false,
        "binop": null
      },
      "value": "enumerable",
      "start": 187,
      "end": 197,
      "loc": {
        "start": {
          "line": 8,
          "column": 6
        },
        "end": {
          "line": 8,
          "column": 16
        }
      }
    },
    {
      "type": {
        "label": ":",
        "beforeExpr": true,
        "startsExpr": false,
        "rightAssociative": false,
        "isLoop": false,
        "isAssign": false,
        "prefix": false,
        "postfix": false,
        "binop": null,
        "updateContext": null
      },
      "start": 197,
      "end": 198,
      "loc": {
        "start": {
          "line": 8,
          "column": 16
        },
        "end": {
          "line": 8,
          "column": 17
        }
      }
    },
    {
      "type": {
        "label": "true",
        "keyword": "true",
        "beforeExpr": false,
        "startsExpr": true,
        "rightAssociative": false,
        "isLoop": false,
        "isAssign": false,
        "prefix": false,
        "postfix": false,
        "binop": null,
        "updateContext": null
      },
      "value": "true",
      "start": 199,
      "end": 203,
      "loc": {
        "start": {
          "line": 8,
          "column": 18
        },
        "end": {
          "line": 8,
          "column": 22
        }
      }
    },
    {
      "type": {
        "label": "}",
        "beforeExpr": false,
        "startsExpr": false,
        "rightAssociative": false,
        "isLoop": false,
        "isAssign": false,
        "prefix": false,
        "postfix": false,
        "binop": null
      },
      "start": 208,
      "end": 209,
      "loc": {
        "start": {
          "line": 9,
          "column": 4
        },
        "end": {
          "line": 9,
          "column": 5
        }
      }
    },
    {
      "type": {
        "label": ")",
        "beforeExpr": false,
        "startsExpr": false,
        "rightAssociative": false,
        "isLoop": false,
        "isAssign": false,
        "prefix": false,
        "postfix": false,
        "binop": null
      },
      "start": 209,
      "end": 210,
      "loc": {
        "start": {
          "line": 9,
          "column": 5
        },
        "end": {
          "line": 9,
          "column": 6
        }
      }
    },
    {
      "type": {
        "label": ";",
        "beforeExpr": true,
        "startsExpr": false,
        "rightAssociative": false,
        "isLoop": false,
        "isAssign": false,
        "prefix": false,
        "postfix": false,
        "binop": null,
        "updateContext": null
      },
      "start": 210,
      "end": 211,
      "loc": {
        "start": {
          "line": 9,
          "column": 6
        },
        "end": {
          "line": 9,
          "column": 7
        }
      }
    },
    {
      "type": {
        "label": "}",
        "beforeExpr": false,
        "startsExpr": false,
        "rightAssociative": false,
        "isLoop": false,
        "isAssign": false,
        "prefix": false,
        "postfix": false,
        "binop": null
      },
      "start": 214,
      "end": 215,
      "loc": {
        "start": {
          "line": 10,
          "column": 2
        },
        "end": {
          "line": 10,
          "column": 3
        }
      }
    },
    {
      "type": {
        "label": "}",
        "beforeExpr": false,
        "startsExpr": false,
        "rightAssociative": false,
        "isLoop": false,
        "isAssign": false,
        "prefix": false,
        "postfix": false,
        "binop": null
      },
      "start": 216,
      "end": 217,
      "loc": {
        "start": {
          "line": 11,
          "column": 0
        },
        "end": {
          "line": 11,
          "column": 1
        }
      }
    },
    {
      "type": {
        "label": "export",
        "keyword": "export",
        "beforeExpr": false,
        "startsExpr": false,
        "rightAssociative": false,
        "isLoop": false,
        "isAssign": false,
        "prefix": false,
        "postfix": false,
        "binop": null,
        "updateContext": null
      },
      "value": "export",
      "start": 219,
      "end": 225,
      "loc": {
        "start": {
          "line": 13,
          "column": 0
        },
        "end": {
          "line": 13,
          "column": 6
        }
      }
    },
    {
      "type": {
        "label": "default",
        "keyword": "default",
        "beforeExpr": true,
        "startsExpr": false,
        "rightAssociative": false,
        "isLoop": false,
        "isAssign": false,
        "prefix": false,
        "postfix": false,
        "binop": null,
        "updateContext": null
      },
      "value": "default",
      "start": 226,
      "end": 233,
      "loc": {
        "start": {
          "line": 13,
          "column": 7
        },
        "end": {
          "line": 13,
          "column": 14
        }
      }
    },
    {
      "type": {
        "label": "name",
        "beforeExpr": false,
        "startsExpr": true,
        "rightAssociative": false,
        "isLoop": false,
        "isAssign": false,
        "prefix": false,
        "postfix": false,
        "binop": null
      },
      "value": "ValidationError",
      "start": 234,
      "end": 249,
      "loc": {
        "start": {
          "line": 13,
          "column": 15
        },
        "end": {
          "line": 13,
          "column": 30
        }
      }
    },
    {
      "type": {
        "label": ";",
        "beforeExpr": true,
        "startsExpr": false,
        "rightAssociative": false,
        "isLoop": false,
        "isAssign": false,
        "prefix": false,
        "postfix": false,
        "binop": null,
        "updateContext": null
      },
      "start": 249,
      "end": 250,
      "loc": {
        "start": {
          "line": 13,
          "column": 30
        },
        "end": {
          "line": 13,
          "column": 31
        }
      }
    },
    {
      "type": {
        "label": "eof",
        "beforeExpr": false,
        "startsExpr": false,
        "rightAssociative": false,
        "isLoop": false,
        "isAssign": false,
        "prefix": false,
        "postfix": false,
        "binop": null,
        "updateContext": null
      },
      "start": 251,
      "end": 251,
      "loc": {
        "start": {
          "line": 14,
          "column": 0
        },
        "end": {
          "line": 14,
          "column": 0
        }
      }
    }
  ]
}